Workbook

Sheet README
A1: Valora - M2 hand-entry template: Shoprite Holdings (SHP), FY2025
A3: SOURCE DOCUMENT
A4: Shoprite Holdings Limited - Annual Financial Statements 2025
A5: 52 weeks ended 29 June 2025. Presentation currency ZAR, figures in Rm (millions).
A6: Authorised for issue by the Board on 1 October 2025.
A8: WHAT YOU MUST DO - this is not finished
A9: 1. Values are pre-filled from the published statements. They are NOT yet verified. Check each against the PDF.
A10: 2. Fill the 'page' column for every row. This is the provenance link - facts.page is NOT NULL in the schema.
A11: 3. Set 'verified' to Y once you have seen the figure on the page with your own eyes.
A12: 4. Open the Checks sheet. Every check must read PASS before this becomes golden dataset.
A13: 5. Add anything you find confusing to Concepts_Discovered - that sheet is the raw material for M2.11.
A15: COLUMN MEANINGS
... A40: FY2025 = 52 weeks ended 29 June 2025. Do not assume period_end is the last day of the fye_month.

Sheet IncomeStatement
A1: M2.5 Consolidated statement of comprehensive income (profit or loss section)
A2: Source: Shoprite Holdings Ltd, Annual Financial Statements 2025 (52 weeks ended 29 June 2025). Values pre-filled from the published statements — VERIFY each against the PDF, then fill 'page' and set 'verified' to Y.
A4: row_id | B4: statement | C4: note_ref | D4: as_reported_label | E4: period | F4: basis | G4: value_as_printed | H4: scale | I4: unit | J4: currency | K4: page | L4: verified | M4: concept_suggestion | N4: notes
A5: 1 | B5: income_statement | C5: 26 | D5: Revenue | E5: FY2025 | F5: as_reported | G5: 256682 | H5: millions | I5: currency | J5: ZAR | M5: revenue_total | N5: Total of sale of merchandise + alternative revenue + interest revenue
A6: 2 | B6: income_statement | C6: 26 | D6: Revenue | E6: FY2024 | F6: restated | G6: 236328 | H6: millions | I6: currency | J6: ZAR | M6: revenue_total | N6: FY2024 comparative RESTATED for discontinued operations (note 45). Previously-reported figures on sheet Restatement_N45
A7: 3 | B7: income_statement | C7: 26 | D7: Sale of merchandise | E7: FY2025 | F7: as_reported | G7: 252701 | H7: millions | I7: currency | J7: ZAR | M7: revenue | N7: The core retail revenue line analysts model
A8: 4 | B8: income_statement | C8: 26 | D8: Sale of merchandise | E8: FY2024 | F8: restated | G8: 232088 | H8: millions | I8: currency | J8: ZAR | M8: revenue | N8: FY2024 comparative RESTATED for discontinued operations (note 45). Previously-reported figures on sheet Restatement_N45
A9: 5 | B9: income_statement | D9: Cost of sales | E9: FY2025 | F9: as_reported | G9: -191259 | H9: millions | I9: currency | J9: ZAR | M9: cost_of_sales | N9: Printed in parentheses = negative. sign_convention 'signed'
A10: 6 | B10: income_statement | D10: Cost of sales | E10: FY2024 | F10: restated | G10: -176549 | H10: millions | I10: currency | J10: ZAR | M10: cost_of_sales | N10: FY2024 comparative RESTATED for discontinued operations (note 45). Previously-reported figures on sheet Restatement_N45
A11: 7 | B11: income_statement | D11: Gross profit | E11: FY2025 | F11: as_reported | G11: 61442 | H11: millions | I11: currency | J11: ZAR | M11: gross_profit | N11: CHECK: sale of merchandise less cost of sales
A12: 8 | B12: income_statement | D12: Gross profit | E12: FY2024 | F12: restated | G12: 55539 | H12: millions | I12: currency | J12: ZAR | M12: gross_profit | N12: FY2024 comparative RESTATED for discontinued operations (note 45). Previously-reported figures on sheet Restatement_N45
A13: 9 | B13: income_statement | C13: 26 | D13: Alternative revenue | E13: FY2025 | F13: as_reported | G13: 3763 | H13: millions | I13: currency | J13: ZAR | M13: alternative_revenue | N13: RENAMED this year from 'other operating income' (footnote 1) - terminology drift, see line_item_id
A14: 10 | B14: income_statement | C14: 26 | D14: Alternative revenue | E14: FY2024 | F14: restated | G14: 3927 | H14: millions | I14: currency | J14: ZAR | M14: alternative_revenue | N14: FY2024 comparative RESTATED for discontinued operations (note 45). Previously-reported figures on sheet Restatement_N45
A15: 11 | B15: income_statement | C15: 26 | D15: Interest revenue | E15: FY2025 | F15: as_reported | G15: 218 | H15: millions | I15: currency | J15: ZAR | M15: interest_revenue
A16: 12 | B16: income_statement | C16: 26 | D16: Interest revenue | E16: FY2024 | F16: restated | G16: 313 | H16: millions | I16: currency | J16: ZAR | M16: interest_revenue | N16: FY2024 comparative RESTATED for discontinued operations (note 45). Previously-reported figures on sheet Restatement_N45
A17: 13 | B17: income_statement | C17: 9 | D17: Share of profit of equity accounted investments | E17: FY2025 | F17: as_reported | G17: 250 | H17: millions | I17: currency | J17: ZAR | M17: equity_accounted_profit
A18: 14 | B18: income_statement | C18: 9 | D18: Share of profit of equity accounted investments | E18: FY2024 | F18: restated | G18: 268 | H18: millions | I18: currency | J18: ZAR | M18: equity_accounted_profit | N18: FY2024 comparative RESTATED for discontinued operations (note 45). Previously-reported figures on sheet Restatement_N45
A19: 15 | B19: income_statement | C19: 27 | D19: Depreciation and amortisation | E19: FY2025 | F19: as_reported | G19: -8012 | H19: millions | I19: currency | J19: ZAR | M19: depreciation_amortisation | N19: Net of amount disclosed in cost of sales (note 27)
A20: 16 | B20: income_statement | C20: 27 | D20: Depreciation and amortisation | E20: FY2024 | F20: restated | G20: -6845 | H20: millions | I20: currency | J20: ZAR | M20: depreciation_amortisation | N20: FY2024 comparative RESTATED for discontinued operations (note 45). Previously-reported figures on sheet Restatement_N45
A21: 17 | B21: income_statement | C21: 28 | D21: Employee benefits | E21: FY2025 | F21: as_reported | G21: -20268 | H21: millions | I21: currency | J21: ZAR | M21: employee_benefits | N21: Net of amount disclosed in cost of sales (note 28)
A22: 18 | B22: income_statement | C22: 28 | D22: Employee benefits | E22: FY2024 | F22: restated | G22: -18289 | H22: millions | I22: currency | J22: ZAR | M22: employee_benefits | N22: FY2024 comparative RESTATED for discontinued operations (note 45). Previously-reported figures on sheet Restatement_N45
A23: 19 | B23: income_statement | C23: 43.4.1 | D23: Credit impairment losses | E23: FY2025 | F23: as_reported | G23: -76 | H23: millions | I23: currency | J23: ZAR | M23: credit_impairment_losses
A24: 20 | B24: income_statement | C24: 43.4.1 | D24: Credit impairment losses | E24: FY2024 | F24: restated | G24: -179 | H24: millions | I24: currency | J24: ZAR | M24: credit_impairment_losses | N24: FY2024 comparative RESTATED for discontinued operations (note 45). Previously-reported figures on sheet Restatement_N45
A25: 21 | B25: income_statement | C25: 30 | D25: Other operating expenses | E25: FY2025 | F25: as_reported | G25: -22366 | H25: millions | I25: currency | J25: ZAR | M25: other_operating_expenses | N25: Net of amount disclosed in cost of sales (note 30)
A26: 22 | B26: income_statement | C26: 30 | D26: Other operating expenses | E26: FY2024 | F26: restated | G26: -21916 | H26: millions | I26: currency | J26: ZAR | M26: other_operating_expenses | N26: FY2024 comparative RESTATED for discontinued operations (note 45). Previously-reported figures on sheet Restatement_N45
A27: 23 | B27: income_statement | D27: Trading profit | E27: FY2025 | F27: as_reported | G27: 14951 | H27: millions | I27: currency | J27: ZAR | M27: trading_profit | N27: COMPANY-DEFINED measure, not IFRS. Defined in policy note 1.1.2(a). Heavily modelled by analysts
A28: 24 | B28: income_statement | D28: Trading profit | E28: FY2024 | F28: restated | G28: 12818 | H28: millions | I28: currency | J28: ZAR | M28: trading_profit | N28: FY2024 comparative RESTATED for discontinued operations (note 45). Previously-reported figures on sheet Restatement_N45
A29: 25 | B29: income_statement | D29: Exchange rate (losses)/gains | E29: FY2025 | F29: as_reported | G29: -3 | H29: millions | I29: currency | J29: ZAR | M29: fx_gains_losses
A30: 26 | B30: income_statement | D30: Exchange rate (losses)/gains | E30: FY2024 | F30: restated | G30: 27 | H30: millions | I30: currency | J30: ZAR | M30: fx_gains_losses | N30: FY2024 comparative RESTATED for discontinued operations (note 45). Previously-reported figures on sheet Restatement_N45
A31: 27 | B31: income_statement | D31: Profit on lease modifications and terminations | E31: FY2025 | F31: as_reported | G31: 95 | H31: millions | I31: currency | J31: ZAR | M31: lease_modification_profit
A32: 28 | B32: income_statement | D32: Profit on lease modifications and terminations | E32: FY2024 | F32: restated | G32: 96 | H32: millions | I32: currency | J32: ZAR | M32: lease_modification_profit | N32: FY2024 comparative RESTATED for discontinued operations (note 45). Previously-reported figures on sheet Restatement_N45
A33: 29 | B33: income_statement | C33: 31 | D33: Items of a capital nature | E33: FY2025 | F33: as_reported | G33: -100 | H33: millions | I33: currency | J33: ZAR | M33: items_of_capital_nature | N33: COMPANY-DEFINED, per SAICA Circular 1/2023 - same circular that governs HEPS
A34: 30 | B34: income_statement | C34: 31 | D34: Items of a capital nature | E34: FY2024 | F34: restated | G34: -279 | H34: millions | I34: currency | J34: ZAR | M34: items_of_capital_nature | N34: FY2024 comparative RESTATED for discontinued operations (note 45). Previously-reported figures on sheet Restatement_N45
A35: 31 | B35: income_statement | C35: 32 | D35: Operating profit | E35: FY2025 | F35: as_reported | G35: 14943 | H35: millions | I35: currency | J35: ZAR | M35: operating_profit
A36: 32 | B36: income_statement | C36: 32 | D36: Operating profit | E36: FY2024 | F36: restated | G36: 12662 | H36: millions | I36: currency | J36: ZAR | M36: operating_profit | N36: FY2024 comparative RESTATED for discontinued operations (note 45). Previously-reported figures on sheet Restatement_N45
A37: 33 | B37: income_statement | D37: Interest received from bank account balances | E37: FY2025 | F37: as_reported | G37: 357 | H37: millions | I37: currency | J37: ZAR | M37: interest_received_bank | N37: Company-defined: call and operating bank balances only (policy 1.1.2(c))
A38: 34 | B38: income_statement | D38: Interest received from bank account balances | E38: FY2024 | F38: restated | G38: 517 | H38: millions | I38: currency | J38: ZAR | M38: interest_received_bank | N38: FY2024 comparative RESTATED for discontinued operations (note 45). Previously-reported figures on sheet Restatement_N45
A39: 35 | B39: income_statement | C39: 33 | D39: Finance costs | E39: FY2025 | F39: as_reported | G39: -5115 | H39: millions | I39: currency | J39: ZAR | M39: finance_costs
A40: 36 | B40: income_statement | C40: 33 | D40: Finance costs | E40: FY2024 | F40: restated | G40: -4153 | H40: millions | I40: currency | J40: ZAR | M40: finance_costs | N40: FY2024 comparative RESTATED for discontinued operations (note 45). Previously-reported figures on sheet Restatement_N45
A41: 37 | B41: income_statement | D41: Profit before income tax | E41: FY2025 | F41: as_reported | G41: 10185 | H41: millions | I41: currency | J41: ZAR | M41: profit_before_tax
A42: 38 | B42: income_statement | D42: Profit before income tax | E42: FY2024 | F42: restated | G42: 9026 | H42: millions | I42: currency | J42: ZAR | M42: profit_before_tax | N42: FY2024 comparative RESTATED for discontinued operations (note 45). Previously-reported figures on sheet Restatement_N45
A43: 39 | B43: income_statement | C43: 34 | D43: Income tax expense | E43: FY2025 | F43: as_reported | G43: -2793 | H43: millions | I43: currency | J43: ZAR | M43: income_tax_expense
A44: 40 | B44: income_statement | C44: 34 | D44: Income tax expense | E44: FY2024 | F44: restated | G44: -2805 | H44: millions | I44: currency | J44: ZAR | M44: income_tax_expense | N44: FY2024 comparative RESTATED for discontinued operations (note 45). Previously-reported figures on sheet Restatement_N45
A45: 41 | B45: income_statement | D45: Profit from continuing operations | E45: FY2025 | F45: as_reported | G45: 7392 | H45: millions | I45: currency | J45: ZAR | M45: profit_continuing_operations
A46: 42 | B46: income_statement | D46: Profit from continuing operations | E46: FY2024 | F46: restated | G46: 6221 | H46: millions | I46: currency | J46: ZAR | M46: profit_continuing_operations | N46: FY2024 comparative RESTATED for discontinued operations (note 45). Previously-reported figures on sheet Restatement_N45
A47: 43 | B47: income_statement | C47: 35 | D47: Profit from discontinued operations | E47: FY2025 | F47: as_reported | G47: 191 | H47: millions | I47: currency | J47: ZAR | M47: profit_discontinued_operations | N47: 2024 printed as em-dash = nil, NOT missing
A48: 44 | B48: income_statement | C48: 35 | D48: Profit from discontinued operations | E48: FY2024 | F48: restated | G48: 0 | H48: millions | I48: currency | J48: ZAR | M48: profit_discontinued_operations | N48: FY2024 comparative RESTATED for discontinued operations (note 45). Previously-reported figures on sheet Restatement_N45
A49: 45 | B49: income_statement | D49: Profit for the year | E49: FY2025 | F49: as_reported | G49: 7583 | H49: millions | I49: currency | J49: ZAR | M49: profit_for_period
A50: 46 | B50: income_statement | D50: Profit for the year | E50: FY2024 | F50: restated | G50: 6221 | H50: millions | I50: currency | J50: ZAR | M50: profit_for_period | N50: FY2024 comparative RESTATED for discontinued operations (note 45). Previously-reported figures on sheet Restatement_N45
A51: 47 | B51: income_statement | D51: Profit attributable to owners of the parent | E51: FY2025 | F51: as_reported | G51: 7585 | H51: millions | I51: currency | J51: ZAR | M51: profit_attributable_owners | N51: Used as numerator in EPS and starting point of HEPS reconciliation
A52: 48 | B52: income_statement | D52: Profit attributable to owners of the parent | E52: FY2024 | F52: restated | G52: 6248 | H52: millions | I52: currency | J52: ZAR | M52: profit_attributable_owners | N52: FY2024 comparative RESTATED for discontinued operations (note 45). Previously-reported figures on sheet Restatement_N45
A53: 49 | B53: income_statement | D53: Profit attributable to non-controlling interest | E53: FY2025 | F53: as_reported | G53: -2 | H53: millions | I53: currency | J53: ZAR | M53: profit_attributable_nci
A54: 50 | B54: income_statement | D54: Profit attributable to non-controlling interest | E54: FY2024 | F54: restated | G54: -27 | H54: millions | I54: currency | J54: ZAR | M54: profit_attributable_nci | N54: FY2024 comparative RESTATED for discontinued operations (note 45). Previously-reported figures on sheet Restatement_N45
A55: 51 | B55: income_statement | C55: 36 | D55: Basic earnings per share from continuing operations (cents) | E55: FY2025 | F55: as_reported | G55: 1367.2 | H55: units | I55: cents_per_share | J55: ZAR | M55: eps_basic_continuing | N55: Per share, in cents - unit_type cents_per_share not currency
A56: 52 | B56: income_statement | C56: 36 | D56: Basic earnings per share from continuing operations (cents) | E56: FY2024 | F56: restated | G56: 1149.5 | H56: units | I56: cents_per_share | J56: ZAR | M56: eps_basic_continuing | N56: Restated
A57: 53 | B57: income_statement | C57: 36 | D57: Diluted earnings per share from continuing operations (cents) | E57: FY2025 | F57: as_reported | G57: 1362.3 | H57: units | I57: cents_per_share | J57: ZAR | M57: eps_diluted_continuing | N57: Per share, in cents - unit_type cents_per_share not currency
A58: 54 | B58: income_statement | C58: 36 | D58: Diluted earnings per share from continuing operations (cents) | E58: FY2024 | F58: restated | G58: 1144.7 | H58: units | I58: cents_per_share | J58: ZAR | M58: eps_diluted_continuing | N58: Restated
A59: 55 | B59: income_statement | C59: 36 | D59: Basic earnings per share (cents) | E59: FY2025 | F59: as_reported | G59: 1401.2 | H59: units | I59: cents_per_share | J59: ZAR | M59: eps_basic | N59: Per share, in cents - unit_type cents_per_share not currency
A60: 56 | B60: income_statement | C60: 36 | D60: Basic earnings per share (cents) | E60: FY2024 | F60: restated | G60: 1148.6 | H60: units | I60: cents_per_share | J60: ZAR | M60: eps_basic | N60: Restated
A61: 57 | B61: income_statement | C61: 36 | D61: Diluted earnings per share (cents) | E61: FY2025 | F61: as_reported | G61: 1396.2 | H61: units | I61: cents_per_share | J61: ZAR | M61: eps_diluted | N61: Per share, in cents - unit_type cents_per_share not currency
A62: 58 | B62: income_statement | C62: 36 | D62: Diluted earnings per share (cents) | E62: FY2024 | F62: restated | G62: 1143.7 | H62: units | I62: cents_per_share | J62: ZAR | M62: eps_diluted | N62: Restated

Sheet BalanceSheet
A1: M2.6 Consolidated statement of financial position
A2: Source: Shoprite Holdings Ltd, Annual Financial Statements 2025 (52 weeks ended 29 June 2025). Values pre-filled from the published statements — VERIFY each against the PDF, then fill 'page' and set 'verified' to Y.
A4: row_id | B4: statement | C4: note_ref | D4: as_reported_label | E4: period | F4: basis | G4: value_as_printed | H4: scale | I4: unit | J4: currency | K4: page | L4: verified | M4: concept_suggestion | N4: notes
A5: 1 | B5: balance_sheet | D5: Non-current assets | E5: FY2025 | F5: as_reported | G5: 72077 | H5: millions | I5: currency | J5: ZAR | M5: total_non_current_assets
A6: 2 | B6: balance_sheet | D6: Non-current assets | E6: FY2024 | F6: as_reported | G6: 62269 | H6: millions | I6: currency | J6: ZAR | M6: total_non_current_assets | N6: IMPORTANT: balance sheet comparative NOT restated (IFRS 5 does not require it) - basis is as_reported, unlike the income statement
A7: 3 | B7: balance_sheet | C7: 3 | D7: Property, plant and equipment | E7: FY2025 | F7: as_reported | G7: 22536 | H7: millions | I7: currency | J7: ZAR | M7: property_plant_equipment
A8: 4 | B8: balance_sheet | C8: 3 | D8: Property, plant and equipment | E8: FY2024 | F8: as_reported | G8: 19672 | H8: millions | I8: currency | J8: ZAR | M8: property_plant_equipment | N8: IMPORTANT: balance sheet comparative NOT restated (IFRS 5 does not require it) - basis is as_reported, unlike the income statement
A9: 5 | B9: balance_sheet | C9: 5 | D9: Investment properties | E9: FY2025 | F9: as_reported | G9: 128 | H9: millions | I9: currency | J9: ZAR | M9: investment_properties
A10: 6 | B10: balance_sheet | C10: 5 | D10: Investment properties | E10: FY2024 | F10: as_reported | G10: 617 | H10: millions | I10: currency | J10: ZAR | M10: investment_properties | N10: IMPORTANT: balance sheet comparative NOT restated (IFRS 5 does not require it) - basis is as_reported, unlike the income statement
A11: 7 | B11: balance_sheet | C11: 6 | D11: Right-of-use assets | E11: FY2025 | F11: as_reported | G11: 36090 | H11: millions | I11: currency | J11: ZAR | M11: right_of_use_assets
A12: 8 | B12: balance_sheet | C12: 6 | D12: Right-of-use assets | E12: FY2024 | F12: as_reported | G12: 30469 | H12: millions | I12: currency | J12: ZAR | M12: right_of_use_assets | N12: IMPORTANT: balance sheet comparative NOT restated (IFRS 5 does not require it) - basis is as_reported, unlike the income statement
A13: 9 | B13: balance_sheet | C13: 7 | D13: Intangible assets | E13: FY2025 | F13: as_reported | G13: 5700 | H13: millions | I13: currency | J13: ZAR | M13: intangible_assets
A14: 10 | B14: balance_sheet | C14: 7 | D14: Intangible assets | E14: FY2024 | F14: as_reported | G14: 4695 | H14: millions | I14: currency | J14: ZAR | M14: intangible_assets | N14: IMPORTANT: balance sheet comparative NOT restated (IFRS 5 does not require it) - basis is as_reported, unlike the income statement
A15: 11 | B15: balance_sheet | C15: 9 | D15: Equity accounted investments | E15: FY2025 | F15: as_reported | G15: 2452 | H15: millions | I15: currency | J15: ZAR | M15: equity_accounted_investments
A16: 12 | B16: balance_sheet | C16: 9 | D16: Equity accounted investments | E16: FY2024 | F16: as_reported | G16: 2478 | H16: millions | I16: currency | J16: ZAR | M16: equity_accounted_investments | N16: IMPORTANT: balance sheet comparative NOT restated (IFRS 5 does not require it) - basis is as_reported, unlike the income statement
A17: 13 | B17: balance_sheet | C17: 10 | D17: Investments at fair value through other comprehensive income | E17: FY2025 | F17: as_reported | G17: 74 | H17: millions | I17: currency | J17: ZAR | M17: investments_fvoci
A18: 14 | B18: balance_sheet | C18: 10 | D18: Investments at fair value through other comprehensive income | E18: FY2024 | F18: as_reported | G18: 67 | H18: millions | I18: currency | J18: ZAR | M18: investments_fvoci | N18: IMPORTANT: balance sheet comparative NOT restated (IFRS 5 does not require it) - basis is as_reported, unlike the income statement
A19: 15 | B19: balance_sheet | C19: 11 | D19: Investment in insurance cell captive arrangements (non-current) | E19: FY2025 | F19: as_reported | G19: 39 | H19: millions | I19: currency | J19: ZAR | M19: insurance_cell_captive_non_current
A20: 16 | B20: balance_sheet | C20: 11 | D20: Investment in insurance cell captive arrangements (non-current) | E20: FY2024 | F20: as_reported | G20: 129 | H20: millions | I20: currency | J20: ZAR | M20: insurance_cell_captive_non_current | N20: IMPORTANT: balance sheet comparative NOT restated (IFRS 5 does not require it) - basis is as_reported, unlike the income statement
A21: 17 | B21: balance_sheet | C21: 12 | D21: Government bonds and bills (non-current) | E21: FY2025 | F21: as_reported | G21: 539 | H21: millions | I21: currency | J21: ZAR | M21: government_bonds_non_current
A22: 18 | B22: balance_sheet | C22: 12 | D22: Government bonds and bills (non-current) | E22: FY2024 | F22: as_reported | G22: 0 | H22: millions | I22: currency | J22: ZAR | M22: government_bonds_non_current | N22: IMPORTANT: balance sheet comparative NOT restated (IFRS 5 does not require it) - basis is as_reported, unlike the income statement
A23: 19 | B23: balance_sheet | C23: 13 | D23: Loans receivable (non-current) | E23: FY2025 | F23: as_reported | G23: 487 | H23: millions | I23: currency | J23: ZAR | M23: loans_receivable_non_current
A24: 20 | B24: balance_sheet | C24: 13 | D24: Loans receivable (non-current) | E24: FY2024 | F24: as_reported | G24: 429 | H24: millions | I24: currency | J24: ZAR | M24: loans_receivable_non_current | N24: IMPORTANT: balance sheet comparative NOT restated (IFRS 5 does not require it) - basis is as_reported, unlike the income statement
A25: 21 | B25: balance_sheet | C25: 14 | D25: Deferred income tax assets | E25: FY2025 | F25: as_reported | G25: 3447 | H25: millions | I25: currency | J25: ZAR | M25: deferred_tax_assets
A26: 22 | B26: balance_sheet | C26: 14 | D26: Deferred income tax assets | E26: FY2024 | F26: as_reported | G26: 3297 | H26: millions | I26: currency | J26: ZAR | M26: deferred_tax_assets | N26: IMPORTANT: balance sheet comparative NOT restated (IFRS 5 does not require it) - basis is as_reported, unlike the income statement
A27: 23 | B27: balance_sheet | C27: 15 | D27: Trade and other receivables (non-current) | E27: FY2025 | F27: as_reported | G27: 585 | H27: millions | I27: currency | J27: ZAR | M27: trade_receivables_non_current
A28: 24 | B28: balance_sheet | C28: 15 | D28: Trade and other receivables (non-current) | E28: FY2024 | F28: as_reported | G28: 416 | H28: millions | I28: currency | J28: ZAR | M28: trade_receivables_non_current | N28: IMPORTANT: balance sheet comparative NOT restated (IFRS 5 does not require it) - basis is as_reported, unlike the income statement
A29: 25 | B29: balance_sheet | D29: Current assets | E29: FY2025 | F29: as_reported | G29: 52867 | H29: millions | I29: currency | J29: ZAR | M29: total_current_assets
A30: 26 | B30: balance_sheet | D30: Current assets | E30: FY2024 | F30: as_reported | G30: 50059 | H30: millions | I30: currency | J30: ZAR | M30: total_current_assets | N30: IMPORTANT: balance sheet comparative NOT restated (IFRS 5 does not require it) - basis is as_reported, unlike the income statement
A31: 27 | B31: balance_sheet | C31: 16 | D31: Inventories | E31: FY2025 | F31: as_reported | G31: 29748 | H31: millions | I31: currency | J31: ZAR | M31: inventories
A32: 28 | B32: balance_sheet | C32: 16 | D32: Inventories | E32: FY2024 | F32: as_reported | G32: 28366 | H32: millions | I32: currency | J32: ZAR | M32: inventories | N32: IMPORTANT: balance sheet comparative NOT restated (IFRS 5 does not require it) - basis is as_reported, unlike the income statement
A33: 29 | B33: balance_sheet | C33: 15 | D33: Trade and other receivables (current) | E33: FY2025 | F33: as_reported | G33: 5706 | H33: millions | I33: currency | J33: ZAR | M33: trade_receivables_current
A34: 30 | B34: balance_sheet | C34: 15 | D34: Trade and other receivables (current) | E34: FY2024 | F34: as_reported | G34: 6298 | H34: millions | I34: currency | J34: ZAR | M34: trade_receivables_current | N34: IMPORTANT: balance sheet comparative NOT restated (IFRS 5 does not require it) - basis is as_reported, unlike the income statement
A35: 31 | B35: balance_sheet | D35: Current income tax assets | E35: FY2025 | F35: as_reported | G35: 740 | H35: millions | I35: currency | J35: ZAR | M35: current_tax_assets
A36: 32 | B36: balance_sheet | D36: Current income tax assets | E36: FY2024 | F36: as_reported | G36: 736 | H36: millions | I36: currency | J36: ZAR | M36: current_tax_assets | N36: IMPORTANT: balance sheet comparative NOT restated (IFRS 5 does not require it) - basis is as_reported, unlike the income statement
A37: 33 | B37: balance_sheet | C37: 11 | D37: Investment in insurance cell captive arrangements (current) | E37: FY2025 | F37: as_reported | G37: 92 | H37: millions | I37: currency | J37: ZAR | M37: insurance_cell_captive_current
A38: 34 | B38: balance_sheet | C38: 11 | D38: Investment in insurance cell captive arrangements (current) | E38: FY2024 | F38: as_reported | G38: 402 | H38: millions | I38: currency | J38: ZAR | M38: insurance_cell_captive_current | N38: IMPORTANT: balance sheet comparative NOT restated (IFRS 5 does not require it) - basis is as_reported, unlike the income statement
A39: 35 | B39: balance_sheet | C39: 12 | D39: Government bonds and bills (current) | E39: FY2025 | F39: as_reported | G39: 33 | H39: millions | I39: currency | J39: ZAR | M39: government_bonds_current
A40: 36 | B40: balance_sheet | C40: 12 | D40: Government bonds and bills (current) | E40: FY2024 | F40: as_reported | G40: 886 | H40: millions | I40: currency | J40: ZAR | M40: government_bonds_current | N40: IMPORTANT: balance sheet comparative NOT restated (IFRS 5 does not require it) - basis is as_reported, unlike the income statement
A41: 37 | B41: balance_sheet | C41: 13 | D41: Loans receivable (current) | E41: FY2025 | F41: as_reported | G41: 1009 | H41: millions | I41: currency | J41: ZAR | M41: loans_receivable_current
A42: 38 | B42: balance_sheet | C42: 13 | D42: Loans receivable (current) | E42: FY2024 | F42: as_reported | G42: 680 | H42: millions | I42: currency | J42: ZAR | M42: loans_receivable_current | N42: IMPORTANT: balance sheet comparative NOT restated (IFRS 5 does not require it) - basis is as_reported, unlike the income statement
A43: 39 | B43: balance_sheet | D43: Restricted cash | E43: FY2025 | F43: as_reported | G43: 5 | H43: millions | I43: currency | J43: ZAR | M43: restricted_cash
A44: 40 | B44: balance_sheet | D44: Restricted cash | E44: FY2024 | F44: as_reported | G44: 3 | H44: millions | I44: currency | J44: ZAR | M44: restricted_cash | N44: IMPORTANT: balance sheet comparative NOT restated (IFRS 5 does not require it) - basis is as_reported, unlike the income statement
A45: 41 | B45: balance_sheet | C45: 43.4.1 | D45: Cash and cash equivalents | E45: FY2025 | F45: as_reported | G45: 9946 | H45: millions | I45: currency | J45: ZAR | M45: cash_and_equivalents
A46: 42 | B46: balance_sheet | C46: 43.4.1 | D46: Cash and cash equivalents | E46: FY2024 | F46: as_reported | G46: 11732 | H46: millions | I46: currency | J46: ZAR | M46: cash_and_equivalents | N46: IMPORTANT: balance sheet comparative NOT restated (IFRS 5 does not require it) - basis is as_reported, unlike the income statement
A47: 43 | B47: balance_sheet | C47: 4 | D47: Assets classified as held for sale | E47: FY2025 | F47: as_reported | G47: 5588 | H47: millions | I47: currency | J47: ZAR | M47: assets_held_for_sale
A48: 44 | B48: balance_sheet | C48: 4 | D48: Assets classified as held for sale | E48: FY2024 | F48: as_reported | G48: 956 | H48: millions | I48: currency | J48: ZAR | M48: assets_held_for_sale | N48: IMPORTANT: balance sheet comparative NOT restated (IFRS 5 does not require it) - basis is as_reported, unlike the income statement
A49: 45 | B49: balance_sheet | D49: Total assets | E49: FY2025 | F49: as_reported | G49: 124944 | H49: millions | I49: currency | J49: ZAR | M49: total_assets
A50: 46 | B50: balance_sheet | D50: Total assets | E50: FY2024 | F50: as_reported | G50: 112328 | H50: millions | I50: currency | J50: ZAR | M50: total_assets | N50: IMPORTANT: balance sheet comparative NOT restated (IFRS 5 does not require it) - basis is as_reported, unlike the income statement
A51: 47 | B51: balance_sheet | C51: 17 | D51: Stated capital | E51: FY2025 | F51: as_reported | G51: 7516 | H51: millions | I51: currency | J51: ZAR | M51: stated_capital
A52: 48 | B52: balance_sheet | C52: 17 | D52: Stated capital | E52: FY2024 | F52: as_reported | G52: 7516 | H52: millions | I52: currency | J52: ZAR | M52: stated_capital | N52: IMPORTANT: balance sheet comparative NOT restated (IFRS 5 does not require it) - basis is as_reported, unlike the income statement
A53: 49 | B53: balance_sheet | C53: 17 | D53: Treasury shares | E53: FY2025 | F53: as_reported | G53: -3756 | H53: millions | I53: currency | J53: ZAR | M53: treasury_shares
A54: 50 | B54: balance_sheet | C54: 17 | D54: Treasury shares | E54: FY2024 | F54: as_reported | G54: -2616 | H54: millions | I54: currency | J54: ZAR | M54: treasury_shares | N54: IMPORTANT: balance sheet comparative NOT restated (IFRS 5 does not require it) - basis is as_reported, unlike the income statement
A55: 51 | B55: balance_sheet | C55: 19 | D55: Reserves | E55: FY2025 | F55: as_reported | G55: 26434 | H55: millions | I55: currency | J55: ZAR | M55: reserves
A56: 52 | B56: balance_sheet | C56: 19 | D56: Reserves | E56: FY2024 | F56: as_reported | G56: 22891 | H56: millions | I56: currency | J56: ZAR | M56: reserves | N56: IMPORTANT: balance sheet comparative NOT restated (IFRS 5 does not require it) - basis is as_reported, unlike the income statement
A57: 53 | B57: balance_sheet | D57: Non-controlling interest | E57: FY2025 | F57: as_reported | G57: -77 | H57: millions | I57: currency | J57: ZAR | M57: non_controlling_interest
A58: 54 | B58: balance_sheet | D58: Non-controlling interest | E58: FY2024 | F58: as_reported | G58: -67 | H58: millions | I58: currency | J58: ZAR | M58: non_controlling_interest | N58: IMPORTANT: balance sheet comparative NOT restated (IFRS 5 does not require it) - basis is as_reported, unlike the income statement
A59: 55 | B59: balance_sheet | D59: Total equity | E59: FY2025 | F59: as_reported | G59: 30117 | H59: millions | I59: currency | J59: ZAR | M59: total_equity
A60: 56 | B60: balance_sheet | D60: Total equity | E60: FY2024 | F60: as_reported | G60: 27724 | H60: millions | I60: currency | J60: ZAR | M60: total_equity | N60: IMPORTANT: balance sheet comparative NOT restated (IFRS 5 does not require it) - basis is as_reported, unlike the income statement
A61: 57 | B61: balance_sheet | D61: Non-current liabilities | E61: FY2025 | F61: as_reported | G61: 50286 | H61: millions | I61: currency | J61: ZAR | M61: total_non_current_liabilities
A62: 58 | B62: balance_sheet | D62: Non-current liabilities | E62: FY2024 | F62: as_reported | G62: 43066 | H62: millions | I62: currency | J62: ZAR | M62: total_non_current_liabilities | N62: IMPORTANT: balance sheet comparative NOT restated (IFRS 5 does not require it) - basis is as_reported, unlike the income statement
A63: 59 | B63: balance_sheet | C63: 20 | D63: Lease liabilities (non-current) | E63: FY2025 | F63: as_reported | G63: 43116 | H63: millions | I63: currency | J63: ZAR | M63: lease_liabilities_non_current
A64: 60 | B64: balance_sheet | C64: 20 | D64: Lease liabilities (non-current) | E64: FY2024 | F64: as_reported | G64: 36702 | H64: millions | I64: currency | J64: ZAR | M64: lease_liabilities_non_current | N64: IMPORTANT: balance sheet comparative NOT restated (IFRS 5 does not require it) - basis is as_reported, unlike the income statement
A65: 61 | B65: balance_sheet | C65: 21 | D65: Borrowings (non-current) | E65: FY2025 | F65: as_reported | G65: 6504 | H65: millions | I65: currency | J65: ZAR | M65: borrowings_non_current
A66: 62 | B66: balance_sheet | C66: 21 | D66: Borrowings (non-current) | E66: FY2024 | F66: as_reported | G66: 5788 | H66: millions | I66: currency | J66: ZAR | M66: borrowings_non_current | N66: IMPORTANT: balance sheet comparative NOT restated (IFRS 5 does not require it) - basis is as_reported, unlike the income statement
A67: 63 | B67: balance_sheet | C67: 14 | D67: Deferred income tax liabilities | E67: FY2025 | F67: as_reported | G67: 8 | H67: millions | I67: currency | J67: ZAR | M67: deferred_tax_liabilities
A68: 64 | B68: balance_sheet | C68: 14 | D68: Deferred income tax liabilities | E68: FY2024 | F68: as_reported | G68: 8 | H68: millions | I68: currency | J68: ZAR | M68: deferred_tax_liabilities | N68: IMPORTANT: balance sheet comparative NOT restated (IFRS 5 does not require it) - basis is as_reported, unlike the income statement
A69: 65 | B69: balance_sheet | C69: 22 | D69: Employee benefit and other provisions (non-current) | E69: FY2025 | F69: as_reported | G69: 582 | H69: millions | I69: currency | J69: ZAR | M69: provisions_non_current
A70: 66 | B70: balance_sheet | C70: 22 | D70: Employee benefit and other provisions (non-current) | E70: FY2024 | F70: as_reported | G70: 482 | H70: millions | I70: currency | J70: ZAR | M70: provisions_non_current | N70: IMPORTANT: balance sheet comparative NOT restated (IFRS 5 does not require it) - basis is as_reported, unlike the income statement
A71: 67 | B71: balance_sheet | C71: 23 | D71: Trade and other payables (non-current) | E71: FY2025 | F71: as_reported | G71: 76 | H71: millions | I71: currency | J71: ZAR | M71: trade_payables_non_current
A72: 68 | B72: balance_sheet | C72: 23 | D72: Trade and other payables (non-current) | E72: FY2024 | F72: as_reported | G72: 86 | H72: millions | I72: currency | J72: ZAR | M72: trade_payables_non_current | N72: IMPORTANT: balance sheet comparative NOT restated (IFRS 5 does not require it) - basis is as_reported, unlike the income statement
A73: 69 | B73: balance_sheet | D73: Current liabilities | E73: FY2025 | F73: as_reported | G73: 44541 | H73: millions | I73: currency | J73: ZAR | M73: total_current_liabilities
A74: 70 | B74: balance_sheet | D74: Current liabilities | E74: FY2024 | F74: as_reported | G74: 41538 | H74: millions | I74: currency | J74: ZAR | M74: total_current_liabilities | N74: IMPORTANT: balance sheet comparative NOT restated (IFRS 5 does not require it) - basis is as_reported, unlike the income statement
A75: 71 | B75: balance_sheet | C75: 23 | D75: Trade and other payables (current) | E75: FY2025 | F75: as_reported | G75: 34084 | H75: millions | I75: currency | J75: ZAR | M75: trade_payables_current
A76: 72 | B76: balance_sheet | C76: 23 | D76: Trade and other payables (current) | E76: FY2024 | F76: as_reported | G76: 32458 | H76: millions | I76: currency | J76: ZAR | M76: trade_payables_current | N76: IMPORTANT: balance sheet comparative NOT restated (IFRS 5 does not require it) - basis is as_reported, unlike the income statement
A77: 73 | B77: balance_sheet | C77: 24 | D77: Contract liabilities | E77: FY2025 | F77: as_reported | G77: 1064 | H77: millions | I77: currency | J77: ZAR | M77: contract_liabilities
A78: 74 | B78: balance_sheet | C78: 24 | D78: Contract liabilities | E78: FY2024 | F78: as_reported | G78: 1219 | H78: millions | I78: currency | J78: ZAR | M78: contract_liabilities | N78: IMPORTANT: balance sheet comparative NOT restated (IFRS 5 does not require it) - basis is as_reported, unlike the income statement
A79: 75 | B79: balance_sheet | C79: 20 | D79: Lease liabilities (current) | E79: FY2025 | F79: as_reported | G79: 3904 | H79: millions | I79: currency | J79: ZAR | M79: lease_liabilities_current
A80: 76 | B80: balance_sheet | C80: 20 | D80: Lease liabilities (current) | E80: FY2024 | F80: as_reported | G80: 3775 | H80: millions | I80: currency | J80: ZAR | M80: lease_liabilities_current | N80: IMPORTANT: balance sheet comparative NOT restated (IFRS 5 does not require it) - basis is as_reported, unlike the income statement
A81: 77 | B81: balance_sheet | C81: 21 | D81: Borrowings (current) | E81: FY2025 | F81: as_reported | G81: 489 | H81: millions | I81: currency | J81: ZAR | M81: borrowings_current
A82: 78 | B82: balance_sheet | C82: 21 | D82: Borrowings (current) | E82: FY2024 | F82: as_reported | G82: 205 | H82: millions | I82: currency | J82: ZAR | M82: borrowings_current | N82: IMPORTANT: balance sheet comparative NOT restated (IFRS 5 does not require it) - basis is as_reported, unlike the income statement
A83: 79 | B83: balance_sheet | D83: Current income tax liabilities | E83: FY2025 | F83: as_reported | G83: 677 | H83: millions | I83: currency | J83: ZAR | M83: current_tax_liabilities
A84: 80 | B84: balance_sheet | D84: Current income tax liabilities | E84: FY2024 | F84: as_reported | G84: 784 | H84: millions | I84: currency | J84: ZAR | M84: current_tax_liabilities | N84: IMPORTANT: balance sheet comparative NOT restated (IFRS 5 does not require it) - basis is as_reported, unlike the income statement
A85: 81 | B85: balance_sheet | C85: 22 | D85: Employee benefit and other provisions (current) | E85: FY2025 | F85: as_reported | G85: 158 | H85: millions | I85: currency | J85: ZAR | M85: provisions_current
A86: 82 | B86: balance_sheet | C86: 22 | D86: Employee benefit and other provisions (current) | E86: FY2024 | F86: as_reported | G86: 202 | H86: millions | I86: currency | J86: ZAR | M86: provisions_current | N86: IMPORTANT: balance sheet comparative NOT restated (IFRS 5 does not require it) - basis is as_reported, unlike the income statement
A87: 83 | B87: balance_sheet | D87: Bank overdrafts and other short-term facilities | E87: FY2025 | F87: as_reported | G87: 1863 | H87: millions | I87: currency | J87: ZAR | M87: bank_overdrafts
A88: 84 | B88: balance_sheet | D88: Bank overdrafts and other short-term facilities | E88: FY2024 | F88: as_reported | G88: 2895 | H88: millions | I88: currency | J88: ZAR | M88: bank_overdrafts | N88: IMPORTANT: balance sheet comparative NOT restated (IFRS 5 does not require it) - basis is as_reported, unlike the income statement
A89: 85 | B89: balance_sheet | C89: 25 | D89: Liabilities directly associated with assets classified as held for sale | E89: FY2025 | F89: as_reported | G89: 2302 | H89: millions | I89: currency | J89: ZAR | M89: liabilities_held_for_sale
A90: 86 | B90: balance_sheet | C90: 25 | D90: Liabilities directly associated with assets classified as held for sale | E90: FY2024 | F90: as_reported | G90: 0 | H90: millions | I90: currency | J90: ZAR | M90: liabilities_held_for_sale | N90: IMPORTANT: balance sheet comparative NOT restated (IFRS 5 does not require it) - basis is as_reported, unlike the income statement
A91: 87 | B91: balance_sheet | D91: Total liabilities | E91: FY2025 | F91: as_reported | G91: 94827 | H91: millions | I91: currency | J91: ZAR | M91: total_liabilities
A92: 88 | B92: balance_sheet | D92: Total liabilities | E92: FY2024 | F92: as_reported | G92: 84604 | H92: millions | I92: currency | J92: ZAR | M92: total_liabilities | N92: IMPORTANT: balance sheet comparative NOT restated (IFRS 5 does not require it) - basis is as_reported, unlike the income statement
A93: 89 | B93: balance_sheet | D93: Total equity and liabilities | E93: FY2025 | F93: as_reported | G93: 124944 | H93: millions | I93: currency | J93: ZAR | M93: total_equity_and_liabilities
A94: 90 | B94: balance_sheet | D94: Total equity and liabilities | E94: FY2024 | F94: as_reported | G94: 112328 | H94: millions | I94: currency | J94: ZAR | M94: total_equity_and_liabilities | N94: IMPORTANT: balance sheet comparative NOT restated (IFRS 5 does not require it) - basis is as_reported, unlike the income statement

Sheet CashFlow
A1: M2.7 Consolidated statement of cash flows
A2: Source: Shoprite Holdings Ltd, Annual Financial Statements 2025 (52 weeks ended 29 June 2025). Values pre-filled from the published statements — VERIFY each against the PDF, then fill 'page' and set 'verified' to Y.
A4: row_id | B4: statement | C4: note_ref | D4: as_reported_label | E4: period | F4: basis | G4: value_as_printed | H4: scale | I4: unit | J4: currency | K4: page | L4: verified | M4: concept_suggestion | N4: notes
A5: 1 | B5: cash_flow | D5: Cash flows from operating activities | E5: FY2025 | F5: as_reported | G5: 10984 | H5: millions | I5: currency | J5: ZAR | M5: cash_from_operating_activities
A6: 2 | B6: cash_flow | D6: Cash flows from operating activities | E6: FY2024 | F6: as_reported | G6: 13841 | H6: millions | I6: currency | J6: ZAR | M6: cash_from_operating_activities | N6: Cash flow comparative NOT restated
A7: 3 | B7: cash_flow | D7: Operating profit (per cash flow statement) | E7: FY2025 | F7: as_reported | G7: 15380 | H7: millions | I7: currency | J7: ZAR | M7: operating_profit_cf | N7: NOTE: 15 380 here vs 14 943 on the income statement - cash flow includes discontinued operations
A8: 4 | B8: cash_flow | D8: Operating profit (per cash flow statement) | E8: FY2024 | F8: as_reported | G8: 12828 | H8: millions | I8: currency | J8: ZAR | M8: operating_profit_cf | N8: Cash flow comparative NOT restated
A9: 5 | B9: cash_flow | D9: Less: investment income and interest revenue earned | E9: FY2025 | F9: as_reported | G9: -767 | H9: millions | I9: currency | J9: ZAR | M9: investment_income_removed
A10: 6 | B10: cash_flow | D10: Less: investment income and interest revenue earned | E10: FY2024 | F10: as_reported | G10: -1009 | H10: millions | I10: currency | J10: ZAR | M10: investment_income_removed | N10: Cash flow comparative NOT restated
A11: 7 | B11: cash_flow | C11: 38.1 | D11: Non-cash items | E11: FY2025 | F11: as_reported | G11: 9589 | H11: millions | I11: currency | J11: ZAR | M11: non_cash_items
A12: 8 | B12: cash_flow | C12: 38.1 | D12: Non-cash items | E12: FY2024 | F12: as_reported | G12: 8557 | H12: millions | I12: currency | J12: ZAR | M12: non_cash_items | N12: Cash flow comparative NOT restated
A13: 9 | B13: cash_flow | C13: 38.2 | D13: Changes in working capital | E13: FY2025 | F13: as_reported | G13: -2312 | H13: millions | I13: currency | J13: ZAR | M13: working_capital_movement
A14: 10 | B14: cash_flow | C14: 38.2 | D14: Changes in working capital | E14: FY2024 | F14: as_reported | G14: 3252 | H14: millions | I14: currency | J14: ZAR | M14: working_capital_movement | N14: Cash flow comparative NOT restated
A15: 11 | B15: cash_flow | D15: Cash generated from operations | E15: FY2025 | F15: as_reported | G15: 21890 | H15: millions | I15: currency | J15: ZAR | M15: cash_generated_from_operations
A16: 12 | B16: cash_flow | D16: Cash generated from operations | E16: FY2024 | F16: as_reported | G16: 23628 | H16: millions | I16: currency | J16: ZAR | M16: cash_generated_from_operations | N16: Cash flow comparative NOT restated
A17: 13 | B17: cash_flow | D17: Interest received | E17: FY2025 | F17: as_reported | G17: 861 | H17: millions | I17: currency | J17: ZAR | M17: interest_received_cf
A18: 14 | B18: cash_flow | D18: Interest received | E18: FY2024 | F18: as_reported | G18: 1212 | H18: millions | I18: currency | J18: ZAR | M18: interest_received_cf | N18: Cash flow comparative NOT restated
A19: 15 | B19: cash_flow | D19: Interest paid | E19: FY2025 | F19: as_reported | G19: -5166 | H19: millions | I19: currency | J19: ZAR | M19: interest_paid_cf
A20: 16 | B20: cash_flow | D20: Interest paid | E20: FY2024 | F20: as_reported | G20: -4305 | H20: millions | I20: currency | J20: ZAR | M20: interest_paid_cf | N20: Cash flow comparative NOT restated
A21: 17 | B21: cash_flow | D21: Dividends received | E21: FY2025 | F21: as_reported | G21: 750 | H21: millions | I21: currency | J21: ZAR | M21: dividends_received_cf
A22: 18 | B22: cash_flow | D22: Dividends received | E22: FY2024 | F22: as_reported | G22: 568 | H22: millions | I22: currency | J22: ZAR | M22: dividends_received_cf | N22: Cash flow comparative NOT restated
A23: 19 | B23: cash_flow | C23: 38.3 | D23: Dividends paid | E23: FY2025 | F23: as_reported | G23: -3985 | H23: millions | I23: currency | J23: ZAR | M23: dividends_paid_cf
A24: 20 | B24: cash_flow | C24: 38.3 | D24: Dividends paid | E24: FY2024 | F24: as_reported | G24: -3743 | H24: millions | I24: currency | J24: ZAR | M24: dividends_paid_cf | N24: Cash flow comparative NOT restated
A25: 21 | B25: cash_flow | C25: 38.4 | D25: Income tax paid | E25: FY2025 | F25: as_reported | G25: -3366 | H25: millions | I25: currency | J25: ZAR | M25: income_tax_paid_cf
A26: 22 | B26: cash_flow | C26: 38.4 | D26: Income tax paid | E26: FY2024 | F26: as_reported | G26: -3519 | H26: millions | I26: currency | J26: ZAR | M26: income_tax_paid_cf | N26: Cash flow comparative NOT restated
A27: 23 | B27: cash_flow | D27: Cash flows utilised by investing activities | E27: FY2025 | F27: as_reported | G27: -7365 | H27: millions | I27: currency | J27: ZAR | M27: cash_from_investing_activities
A28: 24 | B28: cash_flow | D28: Cash flows utilised by investing activities | E28: FY2024 | F28: as_reported | G28: -6779 | H28: millions | I28: currency | J28: ZAR | M28: cash_from_investing_activities | N28: Cash flow comparative NOT restated
A29: 25 | B29: cash_flow | D29: Investment in property, plant and equipment and other intangible assets to expand operations | E29: FY2025 | F29: as_reported | G29: -6320 | H29: millions | I29: currency | J29: ZAR | M29: capex_expansion | N29: Shoprite splits capex expand vs maintain - useful, not all retailers do
A30: 26 | B30: cash_flow | D30: Investment in property, plant and equipment and other intangible assets to expand operations | E30: FY2024 | F30: as_reported | G30: -5718 | H30: millions | I30: currency | J30: ZAR | M30: capex_expansion | N30: Cash flow comparative NOT restated
A31: 27 | B31: cash_flow | D31: Investment in property, plant and equipment and other intangible assets to maintain operations | E31: FY2025 | F31: as_reported | G31: -1679 | H31: millions | I31: currency | J31: ZAR | M31: capex_maintenance
A32: 28 | B32: cash_flow | D32: Investment in property, plant and equipment and other intangible assets to maintain operations | E32: FY2024 | F32: as_reported | G32: -2012 | H32: millions | I32: currency | J32: ZAR | M32: capex_maintenance | N32: Cash flow comparative NOT restated
A33: 29 | B33: cash_flow | D33: Payment for investment in insurance cell captive arrangements | E33: FY2025 | F33: as_reported | G33: -10 | H33: millions | I33: currency | J33: ZAR | M33: payment_insurance_cell
A34: 30 | B34: cash_flow | D34: Payment for investment in insurance cell captive arrangements | E34: FY2024 | F34: as_reported | G34: 0 | H34: millions | I34: currency | J34: ZAR | M34: payment_insurance_cell | N34: Cash flow comparative NOT restated
A35: 31 | B35: cash_flow | D35: Investment in assets classified as held for sale | E35: FY2025 | F35: as_reported | G35: -11 | H35: millions | I35: currency | J35: ZAR | M35: investment_assets_held_for_sale
A36: 32 | B36: cash_flow | D36: Investment in assets classified as held for sale | E36: FY2024 | F36: as_reported | G36: -32 | H36: millions | I36: currency | J36: ZAR | M36: investment_assets_held_for_sale | N36: Cash flow comparative NOT restated
A37: 33 | B37: cash_flow | D37: Investment in convertible loans | E37: FY2025 | F37: as_reported | G37: 0 | H37: millions | I37: currency | J37: ZAR | M37: investment_convertible_loans
A38: 34 | B38: cash_flow | D38: Investment in convertible loans | E38: FY2024 | F38: as_reported | G38: -5 | H38: millions | I38: currency | J38: ZAR | M38: investment_convertible_loans | N38: Cash flow comparative NOT restated
A39: 35 | B39: cash_flow | D39: Payment for investments at fair value through other comprehensive income | E39: FY2025 | F39: as_reported | G39: 0 | H39: millions | I39: currency | J39: ZAR | M39: payment_investments_fvoci
A40: 36 | B40: cash_flow | D40: Payment for investments at fair value through other comprehensive income | E40: FY2024 | F40: as_reported | G40: -4 | H40: millions | I40: currency | J40: ZAR | M40: payment_investments_fvoci | N40: Cash flow comparative NOT restated
A41: 37 | B41: cash_flow | D41: Proceeds on disposal of property, plant and equipment and intangible assets | E41: FY2025 | F41: as_reported | G41: 323 | H41: millions | I41: currency | J41: ZAR | M41: proceeds_disposal_ppe
A42: 38 | B42: cash_flow | D42: Proceeds on disposal of property, plant and equipment and intangible assets | E42: FY2024 | F42: as_reported | G42: 400 | H42: millions | I42: currency | J42: ZAR | M42: proceeds_disposal_ppe | N42: Cash flow comparative NOT restated
A43: 39 | B43: cash_flow | C43: 35.2 | D43: Cash inflows as a result of the disposal of discontinued operations | E43: FY2025 | F43: as_reported | G43: 9 | H43: millions | I43: currency | J43: ZAR | M43: proceeds_disposal_discontinued
A44: 40 | B44: cash_flow | C44: 35.2 | D44: Cash inflows as a result of the disposal of discontinued operations | E44: FY2024 | F44: as_reported | G44: 39 | H44: millions | I44: currency | J44: ZAR | M44: proceeds_disposal_discontinued | N44: Cash flow comparative NOT restated
A45: 41 | B45: cash_flow | D45: Proceeds on disposal of assets classified as held for sale | E45: FY2025 | F45: as_reported | G45: 774 | H45: millions | I45: currency | J45: ZAR | M45: proceeds_disposal_held_for_sale | N45: Includes R772m sale-and-leaseback (footnote 3)
A46: 42 | B46: cash_flow | D46: Proceeds on disposal of assets classified as held for sale | E46: FY2024 | F46: as_reported | G46: 368 | H46: millions | I46: currency | J46: ZAR | M46: proceeds_disposal_held_for_sale | N46: Cash flow comparative NOT restated
A47: 43 | B47: cash_flow | D47: Payments for government bonds and bills | E47: FY2025 | F47: as_reported | G47: -791 | H47: millions | I47: currency | J47: ZAR | M47: payments_government_bonds
A48: 44 | B48: cash_flow | D48: Payments for government bonds and bills | E48: FY2024 | F48: as_reported | G48: -339 | H48: millions | I48: currency | J48: ZAR | M48: payments_government_bonds | N48: Cash flow comparative NOT restated
A49: 45 | B49: cash_flow | D49: Proceeds from government bonds and bills | E49: FY2025 | F49: as_reported | G49: 1061 | H49: millions | I49: currency | J49: ZAR | M49: proceeds_government_bonds
A50: 46 | B50: cash_flow | D50: Proceeds from government bonds and bills | E50: FY2024 | F50: as_reported | G50: 523 | H50: millions | I50: currency | J50: ZAR | M50: proceeds_government_bonds | N50: Cash flow comparative NOT restated
A51: 47 | B51: cash_flow | D51: Loans receivable advanced | E51: FY2025 | F51: as_reported | G51: -635 | H51: millions | I51: currency | J51: ZAR | M51: loans_advanced
A52: 48 | B52: cash_flow | D52: Loans receivable advanced | E52: FY2024 | F52: as_reported | G52: -663 | H52: millions | I52: currency | J52: ZAR | M52: loans_advanced | N52: Cash flow comparative NOT restated
A53: 49 | B53: cash_flow | D53: Loans receivable repaid | E53: FY2025 | F53: as_reported | G53: 578 | H53: millions | I53: currency | J53: ZAR | M53: loans_repaid
A54: 50 | B54: cash_flow | D54: Loans receivable repaid | E54: FY2024 | F54: as_reported | G54: 593 | H54: millions | I54: currency | J54: ZAR | M54: loans_repaid | N54: Cash flow comparative NOT restated
A55: 51 | B55: cash_flow | D55: Proceeds on disposal of investment in associate | E55: FY2025 | F55: as_reported | G55: 1 | H55: millions | I55: currency | J55: ZAR | M55: proceeds_disposal_associate
A56: 52 | B56: cash_flow | D56: Proceeds on disposal of investment in associate | E56: FY2024 | F56: as_reported | G56: 0 | H56: millions | I56: currency | J56: ZAR | M56: proceeds_disposal_associate | N56: Cash flow comparative NOT restated
A57: 53 | B57: cash_flow | D57: Decrease in ring-fenced Angola tax guarantees | E57: FY2025 | F57: as_reported | G57: 0 | H57: millions | I57: currency | J57: ZAR | M57: angola_tax_guarantees
A58: 54 | B58: cash_flow | D58: Decrease in ring-fenced Angola tax guarantees | E58: FY2024 | F58: as_reported | G58: 285 | H58: millions | I58: currency | J58: ZAR | M58: angola_tax_guarantees | N58: Cash flow comparative NOT restated
A59: 55 | B59: cash_flow | C59: 9 | D59: Investment in associate | E59: FY2025 | F59: as_reported | G59: -111 | H59: millions | I59: currency | J59: ZAR | M59: investment_in_associate
A60: 56 | B60: cash_flow | C60: 9 | D60: Investment in associate | E60: FY2024 | F60: as_reported | G60: -119 | H60: millions | I60: currency | J60: ZAR | M60: investment_in_associate | N60: Cash flow comparative NOT restated
A61: 57 | B61: cash_flow | C61: 38.5 | D61: Acquisition of Pingo Delivery (Pty) Ltd | E61: FY2025 | F61: as_reported | G61: -472 | H61: millions | I61: currency | J61: ZAR | M61: acquisition_pingo
A62: 58 | B62: cash_flow | C62: 38.5 | D62: Acquisition of Pingo Delivery (Pty) Ltd | E62: FY2024 | F62: as_reported | G62: 0 | H62: millions | I62: currency | J62: ZAR | M62: acquisition_pingo | N62: Cash flow comparative NOT restated
A63: 59 | B63: cash_flow | D63: Acquisition of other subsidiaries and operations | E63: FY2025 | F63: as_reported | G63: -82 | H63: millions | I63: currency | J63: ZAR | M63: acquisition_other_subsidiaries
A64: 60 | B64: cash_flow | D64: Acquisition of other subsidiaries and operations | E64: FY2024 | F64: as_reported | G64: -44 | H64: millions | I64: currency | J64: ZAR | M64: acquisition_other_subsidiaries | N64: Cash flow comparative NOT restated
A65: 61 | B65: cash_flow | C65: 38.6 | D65: Cash outflow on disposal of investment in subsidiary | E65: FY2025 | F65: as_reported | G65: 0 | H65: millions | I65: currency | J65: ZAR | M65: disposal_subsidiary_outflow
A66: 62 | B66: cash_flow | C66: 38.6 | D66: Cash outflow on disposal of investment in subsidiary | E66: FY2024 | F66: as_reported | G66: -51 | H66: millions | I66: currency | J66: ZAR | M66: disposal_subsidiary_outflow | N66: Cash flow comparative NOT restated
A67: 63 | B67: cash_flow | D67: Cash flows utilised by financing activities | E67: FY2025 | F67: as_reported | G67: -4298 | H67: millions | I67: currency | J67: ZAR | M67: cash_from_financing_activities
A68: 64 | B68: cash_flow | D68: Cash flows utilised by financing activities | E68: FY2024 | F68: as_reported | G68: -4012 | H68: millions | I68: currency | J68: ZAR | M68: cash_from_financing_activities | N68: Cash flow comparative NOT restated
A69: 65 | B69: cash_flow | C69: 20 | D69: Repayment of lease liability obligations | E69: FY2025 | F69: as_reported | G69: -3870 | H69: millions | I69: currency | J69: ZAR | M69: lease_repayments | N69: IFRS 16 - principal portion. Key input to any lease-adjusted cash flow
A70: 66 | B70: cash_flow | C70: 20 | D70: Repayment of lease liability obligations | E70: FY2024 | F70: as_reported | G70: -3386 | H70: millions | I70: currency | J70: ZAR | M70: lease_repayments | N70: Cash flow comparative NOT restated
A71: 67 | B71: cash_flow | D71: Purchase of treasury shares | E71: FY2025 | F71: as_reported | G71: -1432 | H71: millions | I71: currency | J71: ZAR | M71: treasury_share_purchases
A72: 68 | B72: cash_flow | D72: Purchase of treasury shares | E72: FY2024 | F72: as_reported | G72: -239 | H72: millions | I72: currency | J72: ZAR | M72: treasury_share_purchases | N72: Cash flow comparative NOT restated
A73: 69 | B73: cash_flow | D73: Proceeds from treasury shares disposed | E73: FY2025 | F73: as_reported | G73: 38 | H73: millions | I73: currency | J73: ZAR | M73: treasury_share_proceeds
A74: 70 | B74: cash_flow | D74: Proceeds from treasury shares disposed | E74: FY2024 | F74: as_reported | G74: 11 | H74: millions | I74: currency | J74: ZAR | M74: treasury_share_proceeds | N74: Cash flow comparative NOT restated
A75: 71 | B75: cash_flow | C75: 21.1 | D75: Repayment of borrowings | E75: FY2025 | F75: as_reported | G75: -1083 | H75: millions | I75: currency | J75: ZAR | M75: borrowings_repaid
A76: 72 | B76: cash_flow | C76: 21.1 | D76: Repayment of borrowings | E76: FY2024 | F76: as_reported | G76: -1714 | H76: millions | I76: currency | J76: ZAR | M76: borrowings_repaid | N76: Cash flow comparative NOT restated
A77: 73 | B77: cash_flow | C77: 21.1 | D77: Borrowings raised | E77: FY2025 | F77: as_reported | G77: 2049 | H77: millions | I77: currency | J77: ZAR | M77: borrowings_raised
A78: 74 | B78: cash_flow | C78: 21.1 | D78: Borrowings raised | E78: FY2024 | F78: as_reported | G78: 1316 | H78: millions | I78: currency | J78: ZAR | M78: borrowings_raised | N78: Cash flow comparative NOT restated
A79: 75 | B79: cash_flow | D79: Net movement in cash and cash equivalents | E79: FY2025 | F79: as_reported | G79: -679 | H79: millions | I79: currency | J79: ZAR | M79: net_cash_movement
A80: 76 | B80: cash_flow | D80: Net movement in cash and cash equivalents | E80: FY2024 | F80: as_reported | G80: 3050 | H80: millions | I80: currency | J80: ZAR | M80: net_cash_movement | N80: Cash flow comparative NOT restated
A81: 77 | B81: cash_flow | D81: Cash and cash equivalents at the beginning of the year | E81: FY2025 | F81: as_reported | G81: 10037 | H81: millions | I81: currency | J81: ZAR | M81: cash_opening
A82: 78 | B82: cash_flow | D82: Cash and cash equivalents at the beginning of the year | E82: FY2024 | F82: as_reported | G82: 7502 | H82: millions | I82: currency | J82: ZAR | M82: cash_opening | N82: Cash flow comparative NOT restated
A83: 79 | B83: cash_flow | D83: Effect of exchange rate movements and hyperinflation on cash and cash equivalents | E83: FY2025 | F83: as_reported | G83: -35 | H83: millions | I83: currency | J83: ZAR | M83: fx_effect_on_cash
A84: 80 | B84: cash_flow | D84: Effect of exchange rate movements and hyperinflation on cash and cash equivalents | E84: FY2024 | F84: as_reported | G84: -515 | H84: millions | I84: currency | J84: ZAR | M84: fx_effect_on_cash | N84: Cash flow comparative NOT restated
A85: 81 | B85: cash_flow | D85: Cash and cash equivalents at the end of the year | E85: FY2025 | F85: as_reported | G85: 9323 | H85: millions | I85: currency | J85: ZAR | M85: cash_closing | N85: NOTE: 9 323 not 9 946 - this is net of overdrafts and excludes short-term facilities
A86: 82 | B86: cash_flow | D86: Cash and cash equivalents at the end of the year | E86: FY2024 | F86: as_reported | G86: 10037 | H86: millions | I86: currency | J86: ZAR | M86: cash_closing | N86: Cash flow comparative NOT restated

Sheet HEPS
A1: M2.8 Headline earnings reconciliation (note 36) - SAICA Circular 1/2023
A2: Source: Shoprite Holdings Ltd, Annual Financial Statements 2025 (52 weeks ended 29 June 2025). Values pre-filled from the published statements — VERIFY each against the PDF, then fill 'page' and set 'verified' to Y.
A4: row_id | B4: statement | C4: note_ref | D4: as_reported_label | E4: period | F4: basis | G4: value_as_printed | H4: scale | I4: unit | J4: currency | K4: page | L4: verified | M4: concept_suggestion | N4: notes
A5: 1 | B5: heps_reconciliation | C5: 36 | D5: Net profit attributable to owners of the parent [net] | E5: FY2025 | F5: as_reported | G5: 7585 | H5: millions | I5: currency | J5: ZAR | M5: profit_attributable_owners_net | N5: Starting point of the reconciliation
A6: 2 | B6: heps_reconciliation | C6: 36 | D6: Profit from discontinued operations [net] | E6: FY2025 | F6: as_reported | G6: -184 | H6: millions | I6: currency | J6: ZAR | M6: heps_adj_discontinued_net
A7: 3 | B7: heps_reconciliation | C7: 36 | D7: Earnings from continuing operations [net] | E7: FY2025 | F7: as_reported | G7: 7401 | H7: millions | I7: currency | J7: ZAR | M7: earnings_continuing_net
A8: 4 | B8: heps_reconciliation | C8: 36 | D8: Profit on disposal of assets classified as held for sale [gross] | E8: FY2025 | F8: as_reported | G8: -45 | H8: millions | I8: currency | J8: ZAR | M8: heps_adj_disposal_held_for_sale_gross
A9: 5 | B9: heps_reconciliation | C9: 36 | D9: Profit on disposal of assets classified as held for sale [tax effect] | E9: FY2025 | F9: as_reported | G9: 0 | H9: millions | I9: currency | J9: ZAR | M9: heps_adj_disposal_held_for_sale_tax
A10: 6 | B10: heps_reconciliation | C10: 36 | D10: Profit on disposal of assets classified as held for sale [net] | E10: FY2025 | F10: as_reported | G10: -45 | H10: millions | I10: currency | J10: ZAR | M10: heps_adj_disposal_held_for_sale_net
A11: 7 | B11: heps_reconciliation | C11: 36 | D11: Profit on sale and leaseback transaction [gross] | E11: FY2025 | F11: as_reported | G11: -33 | H11: millions | I11: currency | J11: ZAR | M11: heps_adj_sale_leaseback_gross
A12: 8 | B12: heps_reconciliation | C12: 36 | D12: Profit on sale and leaseback transaction [tax effect] | E12: FY2025 | F12: as_reported | G12: 7 | H12: millions | I12: currency | J12: ZAR | M12: heps_adj_sale_leaseback_tax
A13: 9 | B13: heps_reconciliation | C13: 36 | D13: Profit on sale and leaseback transaction [net] | E13: FY2025 | F13: as_reported | G13: -26 | H13: millions | I13: currency | J13: ZAR | M13: heps_adj_sale_leaseback_net
A14: 10 | B14: heps_reconciliation | C14: 36 | D14: Loss on disposal and scrapping of property, plant and equipment and intangible assets [gross] | E14: FY2025 | F14: as_reported | G14: 162 | H14: millions | I14: currency | J14: ZAR | M14: heps_adj_disposal_ppe_gross
A15: 11 | B15: heps_reconciliation | C15: 36 | D15: Loss on disposal and scrapping of property, plant and equipment and intangible assets [tax effect] | E15: FY2025 | F15: as_reported | G15: -32 | H15: millions | I15: currency | J15: ZAR | M15: heps_adj_disposal_ppe_tax
A16: 12 | B16: heps_reconciliation | C16: 36 | D16: Loss on disposal and scrapping of property, plant and equipment and intangible assets [net] | E16: FY2025 | F16: as_reported | G16: 130 | H16: millions | I16: currency | J16: ZAR | M16: heps_adj_disposal_ppe_net
A17: 13 | B17: heps_reconciliation | C17: 36 | D17: Reversal of impairment of property, plant and equipment [gross] | E17: FY2025 | F17: as_reported | G17: -22 | H17: millions | I17: currency | J17: ZAR | M17: heps_adj_impairment_ppe_gross
... A31: 27 | B31: heps_reconciliation | C31: 36 | D31: Insurance claims receivable [net] | E31: FY2025 | F31: as_reported | G31: -30 | H31: millions | I31: currency | J31: ZAR | M31: heps_adj_insurance_claims_net
A32: 28 | B32: heps_reconciliation | C32: 36 | D32: Remeasurement of investment in joint venture to fair value on deemed disposal of Pingo Delivery (Pty) Ltd [gross] | E32: FY2025 | F32: as_reported | G32: -341 | H32: millions | I32: currency | J32: ZAR | M32: heps_adj_jv_remeasurement_gross | N32: Largest single adjustment this year
A33: 29 | B33: heps_reconciliation | C33: 36 | D33: Remeasurement of investment in joint venture to fair value on deemed disposal of Pingo Delivery (Pty) Ltd [tax effect] | E33: FY2025 | F33: as_reported | G33: 0 | H33: millions | I33: currency | J33: ZAR | M33: heps_adj_jv_remeasurement_tax
A34: 30 | B34: heps_reconciliation | C34: 36 | D34: Remeasurement of investment in joint venture to fair value on deemed disposal of Pingo Delivery (Pty) Ltd [net] | E34: FY2025 | F34: as_reported | G34: -341 | H34: millions | I34: currency | J34: ZAR | M34: heps_adj_jv_remeasurement_net
A35: 31 | B35: heps_reconciliation | C35: 36 | D35: Loss on other investing activities [gross] | E35: FY2025 | F35: as_reported | G35: 6 | H35: millions | I35: currency | J35: ZAR | M35: heps_adj_other_investing_gross
A36: 32 | B36: heps_reconciliation | C36: 36 | D36: Loss on other investing activities [tax effect] | E36: FY2025 | F36: as_reported | G36: 0 | H36: millions | I36: currency | J36: ZAR | M36: heps_adj_other_investing_tax
A37: 33 | B37: heps_reconciliation | C37: 36 | D37: Loss on other investing activities [net] | E37: FY2025 | F37: as_reported | G37: 6 | H37: millions | I37: currency | J37: ZAR | M37: heps_adj_other_investing_net
A38: 34 | B38: heps_reconciliation | C38: 36 | D38: Re-measurements attributable to non-controlling interest [gross] | E38: FY2025 | F38: as_reported | G38: -3 | H38: millions | I38: currency | J38: ZAR | M38: heps_adj_nci_gross | N38: Each adjustment is shown gross, then tax effect, then NCI - the treatment an engineer would get wrong
A39: 35 | B39: heps_reconciliation | C39: 36 | D39: Re-measurements attributable to non-controlling interest [tax effect] | E39: FY2025 | F39: as_reported | G39: 0 | H39: millions | I39: currency | J39: ZAR | M39: heps_adj_nci_tax
A40: 36 | B40: heps_reconciliation | C40: 36 | D40: Re-measurements attributable to non-controlling interest [net] | E40: FY2025 | F40: as_reported | G40: -3 | H40: millions | I40: currency | J40: ZAR | M40: heps_adj_nci_net
A41: 37 | B41: heps_reconciliation | C41: 36 | D41: Headline earnings from continuing operations [gross] | E41: FY2025 | F41: as_reported | G41: 97 | H41: millions | I41: currency | J41: ZAR | M41: headline_earnings_continuing_gross
A42: 38 | B42: heps_reconciliation | C42: 36 | D42: Headline earnings from continuing operations [tax effect] | E42: FY2025 | F42: as_reported | G42: -70 | H42: millions | I42: currency | J42: ZAR | M42: headline_earnings_continuing_tax
A43: 39 | B43: heps_reconciliation | C43: 36 | D43: Headline earnings from continuing operations [net] | E43: FY2025 | F43: as_reported | G43: 7428 | H43: millions | I43: currency | J43: ZAR | M43: headline_earnings_continuing_net
A44: 40 | B44: heps_reconciliation | C44: 36 | D44: Profit from discontinued operations (add back) [net] | E44: FY2025 | F44: as_reported | G44: 184 | H44: millions | I44: currency | J44: ZAR | M44: heps_disc_addback_net
A45: 41 | B45: heps_reconciliation | C45: 36 | D45: Items of a capital nature from discontinued operations [gross] | E45: FY2025 | F45: as_reported | G45: 150 | H45: millions | I45: currency | J45: ZAR | M45: heps_adj_capital_discontinued_gross
A46: 42 | B46: heps_reconciliation | C46: 36 | D46: Items of a capital nature from discontinued operations [tax effect] | E46: FY2025 | F46: as_reported | G46: -12 | H46: millions | I46: currency | J46: ZAR | M46: heps_adj_capital_discontinued_tax
A47: 43 | B47: heps_reconciliation | C47: 36 | D47: Items of a capital nature from discontinued operations [net] | E47: FY2025 | F47: as_reported | G47: 138 | H47: millions | I47: currency | J47: ZAR | M47: heps_adj_capital_discontinued_net
A48: 44 | B48: heps_reconciliation | C48: 36 | D48: Headline earnings [gross] | E48: FY2025 | F48: as_reported | G48: 247 | H48: millions | I48: currency | J48: ZAR | M48: headline_earnings_gross | N48: CHECK: headline earnings / weighted average shares x 100 must equal printed HEPS
A49: 45 | B49: heps_reconciliation | C49: 36 | D49: Headline earnings [tax effect] | E49: FY2025 | F49: as_reported | G49: -82 | H49: millions | I49: currency | J49: ZAR | M49: headline_earnings_tax
A50: 46 | B50: heps_reconciliation | C50: 36 | D50: Headline earnings [net] | E50: FY2025 | F50: as_reported | G50: 7750 | H50: millions | I50: currency | J50: ZAR | M50: headline_earnings_net
A51: 47 | B51: heps_reconciliation | C51: 36 | D51: Number of ordinary shares in issue (net of treasury shares) | E51: FY2025 | F51: as_reported | G51: 540523 | H51: thousands | I51: count | J51: ZAR | M51: shares_in_issue | N51: Share COUNT in thousands - unit_type count, not currency
A52: 48 | B52: heps_reconciliation | C52: 36 | D52: Weighted average number of ordinary shares | E52: FY2025 | F52: as_reported | G52: 541440 | H52: thousands | I52: count | J52: ZAR | M52: weighted_average_shares | N52: Share COUNT in thousands - unit_type count, not currency
A53: 49 | B53: heps_reconciliation | C53: 36 | D53: Weighted average number of ordinary shares adjusted for dilution | E53: FY2025 | F53: as_reported | G53: 543396 | H53: thousands | I53: count | J53: ZAR | M53: weighted_average_shares_diluted | N53: Share COUNT in thousands - unit_type count, not currency
A54: 50 | B54: heps_reconciliation | C54: 36 | D54: Headline earnings per share from continuing operations (cents) | E54: FY2025 | F54: as_reported | G54: 1372.1 | H54: units | I54: cents_per_share | J54: ZAR | M54: heps_continuing | N54: THE number SA analysts use
A55: 51 | B55: heps_reconciliation | C55: 36 | D55: Headline earnings per share - discontinued (cents) | E55: FY2025 | F55: as_reported | G55: 59.5 | H55: units | I55: cents_per_share | J55: ZAR | M55: heps_discontinued | N55: THE number SA analysts use
A56: 52 | B56: heps_reconciliation | C56: 36 | D56: Headline earnings per share - total (cents) | E56: FY2025 | F56: as_reported | G56: 1431.6 | H56: units | I56: cents_per_share | J56: ZAR | M56: heps_total | N56: THE number SA analysts use
A57: 53 | B57: heps_reconciliation | C57: 36 | D57: Diluted headline earnings per share - total (cents) | E57: FY2025 | F57: as_reported | G57: 1426.5 | H57: units | I57: cents_per_share | J57: ZAR | M57: heps_diluted_total | N57: THE number SA analysts use

Sheet Segments
A1: M2.9 Operating segment information (note 2.1) - continuing operations
A2: Source: Shoprite Holdings Ltd, Annual Financial Statements 2025 (52 weeks ended 29 June 2025). Values pre-filled from the published statements — VERIFY each against the PDF, then fill 'page' and set 'verified' to Y.
A4: row_id | B4: statement | C4: note_ref | D4: as_reported_label | E4: period | F4: basis | G4: value_as_printed | H4: scale | I4: unit | J4: currency | K4: page | L4: verified | M4: concept_suggestion | N4: notes
A5: 1 | B5: segment_note | C5: 2.1 | D5: Sale of merchandise - external :: Supermarkets RSA | E5: FY2025 | F5: as_reported | G5: 213497 | H5: millions | I5: currency | J5: ZAR | M5: segment_revenue_external
A6: 2 | B6: segment_note | C6: 2.1 | D6: Sale of merchandise - external :: Supermarkets Non-RSA | E6: FY2025 | F6: as_reported | G6: 20568 | H6: millions | I6: currency | J6: ZAR | M6: segment_revenue_external
A7: 3 | B7: segment_note | C7: 2.1 | D7: Sale of merchandise - external :: Other operating segments | E7: FY2025 | F7: as_reported | G7: 18636 | H7: millions | I7: currency | J7: ZAR | M7: segment_revenue_external
A8: 4 | B8: segment_note | C8: 2.1 | D8: Sale of merchandise - external :: Total operating segments | E8: FY2025 | F8: as_reported | G8: 252701 | H8: millions | I8: currency | J8: ZAR | M8: segment_revenue_external
A9: 5 | B9: segment_note | C9: 2.1 | D9: Sale of merchandise - external :: Hyperinflation effect and other reconciling items | E9: FY2025 | F9: as_reported | G9: 0 | H9: millions | I9: currency | J9: ZAR | M9: segment_revenue_external | N9: RECONCILING COLUMN - segments do NOT sum directly to consolidated. M5.7's rule must account for this
A10: 6 | B10: segment_note | C10: 2.1 | D10: Sale of merchandise - external :: Consolidated | E10: FY2025 | F10: as_reported | G10: 252701 | H10: millions | I10: currency | J10: ZAR | M10: segment_revenue_external
A11: 7 | B11: segment_note | C11: 2.1 | D11: Sale of merchandise - inter-segment :: Supermarkets RSA | E11: FY2025 | F11: as_reported | G11: 7483 | H11: millions | I11: currency | J11: ZAR | M11: segment_revenue_intersegment
A12: 8 | B12: segment_note | C12: 2.1 | D12: Sale of merchandise - inter-segment :: Supermarkets Non-RSA | E12: FY2025 | F12: as_reported | G12: 50 | H12: millions | I12: currency | J12: ZAR | M12: segment_revenue_intersegment
A13: 9 | B13: segment_note | C13: 2.1 | D13: Sale of merchandise - inter-segment :: Other operating segments | E13: FY2025 | F13: as_reported | G13: 28 | H13: millions | I13: currency | J13: ZAR | M13: segment_revenue_intersegment
A14: 10 | B14: segment_note | C14: 2.1 | D14: Sale of merchandise - inter-segment :: Total operating segments | E14: FY2025 | F14: as_reported | G14: 7561 | H14: millions | I14: currency | J14: ZAR | M14: segment_revenue_intersegment
A15: 11 | B15: segment_note | C15: 2.1 | D15: Sale of merchandise - inter-segment :: Hyperinflation effect and other reconciling items | E15: FY2025 | F15: as_reported | G15: 0 | H15: millions | I15: currency | J15: ZAR | M15: segment_revenue_intersegment | N15: RECONCILING COLUMN - segments do NOT sum directly to consolidated. M5.7's rule must account for this
A16: 12 | B16: segment_note | C16: 2.1 | D16: Sale of merchandise - inter-segment :: Consolidated | E16: FY2025 | F16: as_reported | G16: 7561 | H16: millions | I16: currency | J16: ZAR | M16: segment_revenue_intersegment
A17: 13 | B17: segment_note | C17: 2.1 | D17: Sale of merchandise - total :: Supermarkets RSA | E17: FY2025 | F17: as_reported | G17: 220980 | H17: millions | I17: currency | J17: ZAR | M17: segment_revenue_total
A18: 14 | B18: segment_note | C18: 2.1 | D18: Sale of merchandise - total :: Supermarkets Non-RSA | E18: FY2025 | F18: as_reported | G18: 20618 | H18: millions | I18: currency | J18: ZAR | M18: segment_revenue_total
A19: 15 | B19: segment_note | C19: 2.1 | D19: Sale of merchandise - total :: Other operating segments | E19: FY2025 | F19: as_reported | G19: 18664 | H19: millions | I19: currency | J19: ZAR | M19: segment_revenue_total
A20: 16 | B20: segment_note | C20: 2.1 | D20: Sale of merchandise - total :: Total operating segments | E20: FY2025 | F20: as_reported | G20: 260262 | H20: millions | I20: currency | J20: ZAR | M20: segment_revenue_total
A21: 17 | B21: segment_note | C21: 2.1 | D21: Sale of merchandise - total :: Hyperinflation effect and other reconciling items | E21: FY2025 | F21: as_reported | G21: 0 | H21: millions | I21: currency | J21: ZAR | M21: segment_revenue_total | N21: RECONCILING COLUMN - segments do NOT sum directly to consolidated. M5.7's rule must account for this
A22: 18 | B22: segment_note | C22: 2.1 | D22: Sale of merchandise - total :: Consolidated | E22: FY2025 | F22: as_reported | G22: 260262 | H22: millions | I22: currency | J22: ZAR | M22: segment_revenue_total
A23: 19 | B23: segment_note | C23: 2.1 | D23: Trading profit/(loss) :: Supermarkets RSA | E23: FY2025 | F23: as_reported | G23: 13904 | H23: millions | I23: currency | J23: ZAR | M23: segment_trading_profit
A24: 20 | B24: segment_note | C24: 2.1 | D24: Trading profit/(loss) :: Supermarkets Non-RSA | E24: FY2025 | F24: as_reported | G24: 644 | H24: millions | I24: currency | J24: ZAR | M24: segment_trading_profit
A25: 21 | B25: segment_note | C25: 2.1 | D25: Trading profit/(loss) :: Other operating segments | E25: FY2025 | F25: as_reported | G25: 652 | H25: millions | I25: currency | J25: ZAR | M25: segment_trading_profit
A26: 22 | B26: segment_note | C26: 2.1 | D26: Trading profit/(loss) :: Total operating segments | E26: FY2025 | F26: as_reported | G26: 15200 | H26: millions | I26: currency | J26: ZAR | M26: segment_trading_profit
A27: 23 | B27: segment_note | C27: 2.1 | D27: Trading profit/(loss) :: Hyperinflation effect and other reconciling items | E27: FY2025 | F27: as_reported | G27: -249 | H27: millions | I27: currency | J27: ZAR | M27: segment_trading_profit | N27: RECONCILING COLUMN - segments do NOT sum directly to consolidated. M5.7's rule must account for this
A28: 24 | B28: segment_note | C28: 2.1 | D28: Trading profit/(loss) :: Consolidated | E28: FY2025 | F28: as_reported | G28: 14951 | H28: millions | I28: currency | J28: ZAR | M28: segment_trading_profit
A29: 25 | B29: segment_note | C29: 2.1 | D29: Interest revenue included in trading profit :: Supermarkets RSA | E29: FY2025 | F29: as_reported | G29: 93 | H29: millions | I29: currency | J29: ZAR | M29: segment_interest_revenue
A30: 26 | B30: segment_note | C30: 2.1 | D30: Interest revenue included in trading profit :: Supermarkets Non-RSA | E30: FY2025 | F30: as_reported | G30: 63 | H30: millions | I30: currency | J30: ZAR | M30: segment_interest_revenue
A31: 27 | B31: segment_note | C31: 2.1 | D31: Interest revenue included in trading profit :: Other operating segments | E31: FY2025 | F31: as_reported | G31: 62 | H31: millions | I31: currency | J31: ZAR | M31: segment_interest_revenue
A32: 28 | B32: segment_note | C32: 2.1 | D32: Interest revenue included in trading profit :: Total operating segments | E32: FY2025 | F32: as_reported | G32: 218 | H32: millions | I32: currency | J32: ZAR | M32: segment_interest_revenue
A33: 29 | B33: segment_note | C33: 2.1 | D33: Interest revenue included in trading profit :: Hyperinflation effect and other reconciling items | E33: FY2025 | F33: as_reported | G33: 0 | H33: millions | I33: currency | J33: ZAR | M33: segment_interest_revenue | N33: RECONCILING COLUMN - segments do NOT sum directly to consolidated. M5.7's rule must account for this
A34: 30 | B34: segment_note | C34: 2.1 | D34: Interest revenue included in trading profit :: Consolidated | E34: FY2025 | F34: as_reported | G34: 218 | H34: millions | I34: currency | J34: ZAR | M34: segment_interest_revenue
A35: 31 | B35: segment_note | C35: 2.1 | D35: Depreciation and amortisation :: Supermarkets RSA | E35: FY2025 | F35: as_reported | G35: 8156 | H35: millions | I35: currency | J35: ZAR | M35: segment_depreciation_amortisation
A36: 32 | B36: segment_note | C36: 2.1 | D36: Depreciation and amortisation :: Supermarkets Non-RSA | E36: FY2025 | F36: as_reported | G36: 755 | H36: millions | I36: currency | J36: ZAR | M36: segment_depreciation_amortisation
A37: 33 | B37: segment_note | C37: 2.1 | D37: Depreciation and amortisation :: Other operating segments | E37: FY2025 | F37: as_reported | G37: 133 | H37: millions | I37: currency | J37: ZAR | M37: segment_depreciation_amortisation
A38: 34 | B38: segment_note | C38: 2.1 | D38: Depreciation and amortisation :: Total operating segments | E38: FY2025 | F38: as_reported | G38: 9044 | H38: millions | I38: currency | J38: ZAR | M38: segment_depreciation_amortisation
A39: 35 | B39: segment_note | C39: 2.1 | D39: Depreciation and amortisation :: Hyperinflation effect and other reconciling items | E39: FY2025 | F39: as_reported | G39: 23 | H39: millions | I39: currency | J39: ZAR | M39: segment_depreciation_amortisation | N39: RECONCILING COLUMN - segments do NOT sum directly to consolidated. M5.7's rule must account for this
A40: 36 | B40: segment_note | C40: 2.1 | D40: Depreciation and amortisation :: Consolidated | E40: FY2025 | F40: as_reported | G40: 9067 | H40: millions | I40: currency | J40: ZAR | M40: segment_depreciation_amortisation
A41: 37 | B41: segment_note | C41: 2.1 | D41: Total assets :: Supermarkets RSA | E41: FY2025 | F41: as_reported | G41: 99765 | H41: millions | I41: currency | J41: ZAR | M41: segment_total_assets
A42: 38 | B42: segment_note | C42: 2.1 | D42: Total assets :: Supermarkets Non-RSA | E42: FY2025 | F42: as_reported | G42: 11037 | H42: millions | I42: currency | J42: ZAR | M42: segment_total_assets
A43: 39 | B43: segment_note | C43: 2.1 | D43: Total assets :: Other operating segments | E43: FY2025 | F43: as_reported | G43: 7264 | H43: millions | I43: currency | J43: ZAR | M43: segment_total_assets
A44: 40 | B44: segment_note | C44: 2.1 | D44: Total assets :: Total operating segments | E44: FY2025 | F44: as_reported | G44: 118066 | H44: millions | I44: currency | J44: ZAR | M44: segment_total_assets
A45: 41 | B45: segment_note | C45: 2.1 | D45: Total assets :: Hyperinflation effect and other reconciling items | E45: FY2025 | F45: as_reported | G45: 583 | H45: millions | I45: currency | J45: ZAR | M45: segment_total_assets | N45: RECONCILING COLUMN - segments do NOT sum directly to consolidated. M5.7's rule must account for this
A46: 42 | B46: segment_note | C46: 2.1 | D46: Total assets :: Consolidated | E46: FY2025 | F46: as_reported | G46: 118649 | H46: millions | I46: currency | J46: ZAR | M46: segment_total_assets

Sheet Restatement_N45
A1: Note 45 - FY2024 comparatives restated for discontinued operations
A2: Source: Shoprite Holdings Ltd, Annual Financial Statements 2025 (52 weeks ended 29 June 2025). Values pre-filled from the published statements — VERIFY each against the PDF, then fill 'page' and set 'verified' to Y.
A3: THIS IS THE BITEMPORAL TEST CASE. Same company, same fiscal year, two correct values. The as_reported rows were true until the FY2025 AFS was published; the restated rows are true from then on. Note that 'Profit for the year' is UNCHANGED - the restatement reclassifies between continuing and discontinued, it does not change total profit.
A4: row_id | B4: statement | C4: note_ref | D4: as_reported_label | E4: period | F4: basis | G4: value_as_printed | H4: scale | I4: unit | J4: currency | K4: page | L4: verified | M4: concept_suggestion | N4: notes
A5: 1 | B5: income_statement | C5: 45 | D5: Revenue | E5: FY2024 | F5: as_reported | G5: 246082 | H5: millions | I5: currency | J5: ZAR | M5: revenue | N5: PREVIOUSLY REPORTED in the FY2024 annual report - what Valora would have believed until Oct 2025
A6: 2 | B6: income_statement | C6: 45 | D6: Revenue | E6: FY2024 | F6: restated | G6: 236328 | H6: millions | I6: currency | J6: ZAR | M6: revenue | N6: RESTATED in the FY2025 annual report for discontinued operations - what Valora believes now
A7: 3 | B7: income_statement | C7: 45 | D7: Sale of merchandise | E7: FY2024 | F7: as_reported | G7: 240718 | H7: millions | I7: currency | J7: ZAR | M7: sale_of_merchandise | N7: PREVIOUSLY REPORTED in the FY2024 annual report - what Valora would have believed until Oct 2025
A8: 4 | B8: income_statement | C8: 45 | D8: Sale of merchandise | E8: FY2024 | F8: restated | G8: 232088 | H8: millions | I8: currency | J8: ZAR | M8: sale_of_merchandise | N8: RESTATED in the FY2025 annual report for discontinued operations - what Valora believes now
A9: 5 | B9: income_statement | C9: 45 | D9: Cost of sales | E9: FY2024 | F9: as_reported | G9: -182968 | H9: millions | I9: currency | J9: ZAR | M9: cost_of_sales | N9: PREVIOUSLY REPORTED in the FY2024 annual report - what Valora would have believed until Oct 2025
A10: 6 | B10: income_statement | C10: 45 | D10: Cost of sales | E10: FY2024 | F10: restated | G10: -176549 | H10: millions | I10: currency | J10: ZAR | M10: cost_of_sales | N10: RESTATED in the FY2025 annual report for discontinued operations - what Valora believes now
A11: 7 | B11: income_statement | C11: 45 | D11: Gross profit | E11: FY2024 | F11: as_reported | G11: 57750 | H11: millions | I11: currency | J11: ZAR | M11: gross_profit | N11: PREVIOUSLY REPORTED in the FY2024 annual report - what Valora would have believed until Oct 2025
A12: 8 | B12: income_statement | C12: 45 | D12: Gross profit | E12: FY2024 | F12: restated | G12: 55539 | H12: millions | I12: currency | J12: ZAR | M12: gross_profit | N12: RESTATED in the FY2025 annual report for discontinued operations - what Valora believes now
A13: 9 | B13: income_statement | C13: 45 | D13: Trading profit | E13: FY2024 | F13: as_reported | G13: 13399 | H13: millions | I13: currency | J13: ZAR | M13: trading_profit | N13: PREVIOUSLY REPORTED in the FY2024 annual report - what Valora would have believed until Oct 2025
A14: 10 | B14: income_statement | C14: 45 | D14: Trading profit | E14: FY2024 | F14: restated | G14: 12818 | H14: millions | I14: currency | J14: ZAR | M14: trading_profit | N14: RESTATED in the FY2025 annual report for discontinued operations - what Valora believes now
A15: 11 | B15: income_statement | C15: 45 | D15: Operating profit | E15: FY2024 | F15: as_reported | G15: 13156 | H15: millions | I15: currency | J15: ZAR | M15: operating_profit | N15: PREVIOUSLY REPORTED in the FY2024 annual report - what Valora would have believed until Oct 2025
A16: 12 | B16: income_statement | C16: 45 | D16: Operating profit | E16: FY2024 | F16: restated | G16: 12662 | H16: millions | I16: currency | J16: ZAR | M16: operating_profit | N16: RESTATED in the FY2025 annual report for discontinued operations - what Valora believes now
... A24: 20 | B24: income_statement | C24: 45 | D24: Profit for the year | E24: FY2024 | F24: restated | G24: 6221 | H24: millions | I24: currency | J24: ZAR | M24: profit_for_the_year | N24: RESTATED in the FY2025 annual report for discontinued operations - what Valora believes now

Sheet Checks
A1: Validation checks - previews the M5 rule set
A2: If any check is FAIL, a value was transcribed wrong. Fix it before this becomes golden dataset.
A4: # | B4: Check | C4: Expected | D4: Computed | E4: Difference | F4: Result | G4: M5 rule
A5: 1 | B5: Balance sheet balances (FY2025) | C5: ='BalanceSheet'!G49 | D5: ='BalanceSheet'!G59+'BalanceSheet'!G91 | E5: =C5-D5 | F5: =IF(ABS(E5)<0.6,"PASS","FAIL") | G5: 5.3
A6: 2 | B6: Balance sheet balances (FY2024) | C6: ='BalanceSheet'!G50 | D6: ='BalanceSheet'!G60+'BalanceSheet'!G92 | E6: =C6-D6 | F6: =IF(ABS(E6)<0.6,"PASS","FAIL") | G6: 5.3
A7: 3 | B7: Gross profit = sale of merchandise less cost of sales (FY2025) | C7: ='IncomeStatement'!G11 | D7: ='IncomeStatement'!G7+'IncomeStatement'!G9 | E7: =C7-D7 | F7: =IF(ABS(E7)<0.6,"PASS","FAIL") | G7: 5.5
A8: 4 | B8: Gross profit = sale of merchandise less cost of sales (FY2024) | C8: ='IncomeStatement'!G12 | D8: ='IncomeStatement'!G8+'IncomeStatement'!G10 | E8: =C8-D8 | F8: =IF(ABS(E8)<0.6,"PASS","FAIL") | G8: 5.5
A9: 5 | B9: Revenue = merchandise + alternative + interest (FY2025) | C9: ='IncomeStatement'!G5 | D9: ='IncomeStatement'!G7+'IncomeStatement'!G13+'IncomeStatement'!G15 | E9: =C9-D9 | F9: =IF(ABS(E9)<0.6,"PASS","FAIL") | G9: 5.5
A10: 6 | B10: Profit for the year = continuing + discontinued (FY2025) | C10: ='IncomeStatement'!G49 | D10: ='IncomeStatement'!G45+'IncomeStatement'!G47 | E10: =C10-D10 | F10: =IF(ABS(E10)<0.6,"PASS","FAIL") | G10: 5.5
A11: 7 | B11: Profit attributable: owners + NCI = profit for year (FY2025) | C11: ='IncomeStatement'!G49 | D11: ='IncomeStatement'!G51+'IncomeStatement'!G53 | E11: =C11-D11 | F11: =IF(ABS(E11)<0.6,"PASS","FAIL") | G11: 5.5
A12: 8 | B12: Cash flow ties: opening + movement + FX = closing (FY2025) | C12: ='CashFlow'!G85 | D12: ='CashFlow'!G81+'CashFlow'!G79+'CashFlow'!G83 | E12: =C12-D12 | F12: =IF(ABS(E12)<0.6,"PASS","FAIL") | G12: 5.4
A13: 9 | B13: Segments + reconciling = consolidated trading profit (FY2025) | C13: ='Segments'!G28 | D13: ='Segments'!G26+'Segments'!G27 | E13: =C13-D13 | F13: =IF(ABS(E13)<0.6,"PASS","FAIL") | G13: 5.7
A14: 10 | B14: Segments sum to total operating segments - revenue (FY2025) | C14: ='Segments'!G8 | D14: ='Segments'!G5+'Segments'!G6+'Segments'!G7 | E14: =C14-D14 | F14: =IF(ABS(E14)<0.6,"PASS","FAIL") | G14: 5.7
A15: 11 | B15: HEPS foots: headline earnings / weighted avg shares x 100 (FY2025) | C15: ='HEPS'!G56 | D15: ='HEPS'!G50/'HEPS'!G52*100000 | E15: =C15-D15 | F15: =IF(ABS(E15)<0.6,"PASS","FAIL") | G15: 5.6
A16: 12 | B16: Restatement: total profit unchanged by reclassification (FY2024) | C16: ='Restatement_N45'!G23 | D16: ='Restatement_N45'!G24 | E16: =C16-D16 | F16: =IF(ABS(E16)<0.6,"PASS","FAIL") | G16: 5.9
B18: Tolerance 0.6 absorbs the rounding inherent in figures presented in Rm. A real difference will be far larger.

Sheet Concepts_Discovered
A1: # | B1: Observation | C1: Where seen | D1: Why it matters for the taxonomy | E1: Decision needed?
A2: 1 | B2: 'Alternative revenue' was called 'other operating income' last year | C2: Income statement footnote 1 | D2: Same concept, different label across years. Proves why facts carry line_item_id. | E2: No - already handled
A3: 2 | B3: Revenue has three components, only one is 'sale of merchandise' | C3: Income statement / note 26 | D3: An analyst modelling 'revenue' almost always means sale of merchandise. Which one is the concept 'revenue'? | E3: YES
A4: 3 | B4: Trading profit is company-defined, not IFRS | C4: Policy note 1.1.2(a) | D4: Comparable across years for Shoprite; may not be comparable across companies. M8.7 problem. | E4: YES
A5: 4 | B5: Items of a capital nature defined by SAICA Circular 1/2023 | C5: Policy note 1.1.2(b) | D5: Directly ties the income statement to the HEPS reconciliation. Circular version can change between years. | E5: YES
A6: 5 | B6: Segments do not sum to consolidated | C6: Note 2.1 | D6: A 'Hyperinflation effect and other reconciling items' column absorbs the difference. M5.7 must allow it. | E6: YES
A7: 6 | B7: Balance sheet comparative not restated, income statement was | C7: Note 45 / SOFP footnote | D7: basis must be per-fact not per-document. | E7: No - decided
A8: 7 | B8: Cash flow 'operating profit' 15 380 differs from income statement 14 943 | C8: Cash flow vs income statement | D8: Cash flow includes discontinued operations; income statement separates them. Same label, different scope. | E8: YES
A9: 8 | B9: Closing cash 9 323 differs from balance sheet cash 9 946 | C9: Cash flow reconciliation | D9: Cash flow closing is net of overdrafts; short-term facilities excluded from FY2025 and prior year. | E9: YES
A10: 9 | B10: Ghana is hyperinflationary (IAS 29), Angola ceased to be | C10: Policy note 1.1 / 1.5 | D10: Hyperinflation adjustments flow through several lines. Affects comparability across years. | E10: YES
A11: 10 | B11: Sale of merchandise disaggregated by banner and by liquor | C11: Note 26.1 | D11: Shoprite/Usave/Checkers/LiquorShop splits - retail-specific operational concepts. | E11: YES
A12: 11 | B12: Sixty60 sales disclosed separately (R18.9bn) | C12: Note 26.1 footnote 16 | D12: Analysts care a lot about this. Is it a concept or a segment? | E12: YES
B14: Add your own as you verify. Anything that made you pause belongs here.
